{
  "description": "Complete Android-style device with A/B, dm-verity, and LUKS",
  "version": "1.0.0",
  "author": "Device Provisioning Team",
  "build_date": "2025-10-31",
  
  "device": {
    "class": "rpi5",
    "variant": "8GB",
    "serial": "RPI5-2024-12345",
    "storage": {
      "type": "emmc",
      "sector_size": 512,
      "capacity": 64,
      "device_path": "/dev/mmcblk0"
    }
  },
  
  "layout": {
    "partitiontable": {
      "label": "gpt",
      "id": "deadbeef-dead-beef-dead-beefdeadbeef",
      "alignment": 4194304,
      "slots": {
        "enabled": true,
        "count": 2,
        "suffix": ["_a", "_b"],
        "default_slot": "a",
        "boot_control": {
          "metadata_partition": "misc",
          "retry_count": 3
        }
      }
    },
    
    "partitions": [
      {
        "name": "boot",
        "slotted": true,
        "size": 268435456,
        "typecode": "0fc63daf-8483-4772-8e79-3d69d8477de4",
        "gptlabel": "boot",
        "gptuuid": "auto",
        "simg": "boot.simg",
        "verity": {
          "enabled": true,
          "mode": "appended",
          "data_size": 260046848,
          "hash_algorithm": "sha256",
          "block_size": 4096
        },
        "description": "Kernel, device tree, initramfs"
      },
      
      {
        "name": "system",
        "slotted": true,
        "size": 4294967296,
        "typecode": "0fc63daf-8483-4772-8e79-3d69d8477de4",
        "gptlabel": "system",
        "gptuuid": "auto",
        "simg": "system.simg",
        "verity": {
          "enabled": true,
          "mode": "appended",
          "data_size": 4185677824,
          "hash_algorithm": "sha256",
          "block_size": 4096
        },
        "description": "Android/Linux system partition"
      },
      
      {
        "name": "vendor",
        "slotted": true,
        "size": 1073741824,
        "typecode": "0fc63daf-8483-4772-8e79-3d69d8477de4",
        "gptlabel": "vendor",
        "gptuuid": "auto",
        "simg": "vendor.simg",
        "verity": {
          "enabled": true,
          "mode": "appended",
          "data_size": 1020054528,
          "hash_algorithm": "sha256",
          "block_size": 4096
        },
        "description": "Vendor-specific binaries and firmware"
      },
      
      {
        "name": "product",
        "slotted": true,
        "size": 536870912,
        "typecode": "0fc63daf-8483-4772-8e79-3d69d8477de4",
        "gptlabel": "product",
        "gptuuid": "auto",
        "simg": "product.simg",
        "verity": {
          "enabled": true,
          "mode": "appended",
          "data_size": 514850816,
          "hash_algorithm": "sha256",
          "block_size": 4096
        },
        "description": "Product-specific apps and customization"
      },
      
      {
        "name": "misc",
        "slotted": false,
        "size": 4194304,
        "typecode": "0fc63daf-8483-4772-8e79-3d69d8477de4",
        "gptlabel": "misc",
        "description": "Bootloader messages and A/B metadata"
      },
      
      {
        "name": "metadata",
        "slotted": false,
        "size": 16777216,
        "typecode": "0fc63daf-8483-4772-8e79-3d69d8477de4",
        "gptlabel": "metadata",
        "description": "Encryption metadata"
      },
      
      {
        "name": "cache",
        "slotted": false,
        "size": 268435456,
        "typecode": "0fc63daf-8483-4772-8e79-3d69d8477de4",
        "gptlabel": "cache",
        "description": "OTA update cache"
      },
      
      {
        "name": "userdata",
        "slotted": false,
        "expand_to_fit": true,
        "typecode": "0fc63daf-8483-4772-8e79-3d69d8477de4",
        "gptlabel": "userdata",
        "luks": {
          "version": 2,
          "cipher": "aes-xts-plain64",
          "key_size": 256,
          "hash": "sha256",
          "sector_size": 512,
          "mname": "userdata_crypt",
          "label": "userdata_encrypted",
          "uuid": "auto"
        },
        "description": "User data - encrypted, shared between slots"
      }
    ]
  },
  
  "provisioning": {
    "skip_partitions": [],
    "verify_after_flash": true,
    "secure_erase_before": true,
    "save_hashes_to": "/persistent/verity_hashes.json"
  },
  
  "metadata": {
    "build_id": "RPI5-2025-001",
    "build_type": "production",
    "security_level": "verified_boot",
    "notes": [
      "All system partitions verified with dm-verity",
      "A/B slots for seamless updates",
      "Userdata encrypted with LUKS2",
      "Automatic rollback on boot failure"
    ]
  }
}

